{
  "user_data" : {
    "-MxiF0MAitO7Zozb-4QP" : {
      "contact" : "Euro",
      "firstDose" : "Pfizer",
      "firstname" : "Euro",
      "lastname" : "Euro",
      "secondDose" : "Pfizer",
      "vaccineNum" : 2
    },
    "-MxiF3023hbuFjRJbFNp" : {
      "contact" : "Euro",
      "firstDose" : "Pfizer",
      "firstname" : "Euro",
      "lastname" : "Euro",
      "secondDose" : "Pfizer",
      "vaccineNum" : 2
    },
    "-MxiF3Ndkc99rfD8Chl1" : {
      "contact" : "Euro",
      "firstDose" : "Pfizer",
      "firstname" : "Euro",
      "lastname" : "Euro",
      "secondDose" : "Pfizer",
      "vaccineNum" : 2
    },
    "-MxiF3gXEghJgpA3P1bl" : {
      "contact" : "Euro",
      "firstDose" : "Pfizer",
      "firstname" : "Euro",
      "lastname" : "Euro",
      "secondDose" : "Pfizer",
      "vaccineNum" : 2
    },
    "-MxiF46cniq7soYf3J8z" : {
      "contact" : "Euro",
      "firstDose" : "Pfizer",
      "firstname" : "Euro",
      "lastname" : "Euro",
      "secondDose" : "Pfizer",
      "vaccineNum" : 2
    },
    "-MxiF4eZFRpKfj-yWUGn" : {
      "contact" : "Euro",
      "firstDose" : "Pfizer",
      "firstname" : "Euro",
      "lastname" : "Euro",
      "secondDose" : "Pfizer",
      "vaccineNum" : 2
    }
  }
}
